wonkai/__init__.py
wonkai/Chat/__init__.py
wonkai/Chat/Chat.py
wonkai/Chat/ChatFunction.py
wonkai/Chat/ChatFunctionMultiple.py
wonkai/Dict/__init__.py
wonkai/Dict/dict.py
wonkai/DocReader/__init__.py
wonkai/DocReader/DocReader.py
wonkai/MailToMail/__init__.py
wonkai/MailToMail/MailToMail.py
wonkai/Prompt/__init__.py
wonkai/Prompt/standalone_question.py
wonkai/ResultAnalyser/__init__.py
wonkai/ResultAnalyser/ResultAnalyser.py
wonkai/ResultAnalyser/ResultComparator.py
wonkai/ResultAnalyser/ResultMemory.py
wonkai/TopicToTopic/__init__.py
wonkai/Vectorizer/__init__.py
wonkai/Vectorizer/Vectorizer.py
wonkai/Vectorizer/VectorizerCS.py
wonkai-0.2.13.dist-info/METADATA
wonkai-0.2.13.dist-info/WHEEL
wonkai-0.2.13.dist-info/RECORD
