Metadata-Version: 2.1
Name: wonkai
Version: 0.2.13
Summary: 
Author: AntoinePercy
Author-email: antoinepercy@hotmail.com
Requires-Python: >=3.9,<3.12
Classifier: Programming Language :: Python :: 3
Classifier: Programming Language :: Python :: 3.9
Classifier: Programming Language :: Python :: 3.10
Classifier: Programming Language :: Python :: 3.11
Requires-Dist: azure-search-documents (==11.4.0b9)
Requires-Dist: docx (>=0.2.4,<0.3.0)
Requires-Dist: langchain (>=0.0.304,<0.0.305)
Requires-Dist: numpy (>=1.26.0,<2.0.0)
Requires-Dist: openai (>=0.28.1,<0.29.0)
Requires-Dist: pandas (>=2.1.1,<3.0.0)
Requires-Dist: pendulum (>=2.1.2,<3.0.0)
Requires-Dist: pypdf2 (>=3.0.1,<4.0.0)
Requires-Dist: tiktoken (>=0.5.1,<0.6.0)
